<PAMDataset>
  <PAMRasterBand band="1">
    <Description>fagaalu_slope</Description>
    <Histograms>
      <HistItem>
        <HistMin>0</HistMin>
        <HistMax>71.91782379150391</HistMax>
        <BucketCount>256</BucketCount>
        <IncludeOutOfRange>1</IncludeOutOfRange>
        <Approximate>0</Approximate>
        <HistCounts>367|0|0|207|0|55|0|42|231|0|309|221|80|0|166|13|59|118|90|84|108|89|130|43|0|116|42|65|101|46|90|32|85|38|0|87|41|40|42|92|49|38|61|55|47|58|53|97|19|106|95|36|90|82|81|77|143|70|49|182|84|64|129|79|99|105|121|73|117|178|154|47|163|131|74|224|91|145|105|161|115|144|162|119|176|116|198|174|215|90|205|187|137|194|183|171|257|151|155|218|223|186|266|144|207|156|193|275|220|203|232|224|260|258|177|264|239|285|200|200|346|149|290|245|229|294|233|309|185|261|243|176|330|155|267|186|227|199|242|200|240|221|151|231|148|198|116|227|129|176|118|161|113|126|113|112|123|86|113|89|109|84|103|79|81|78|66|88|68|58|68|40|63|49|50|52|38|33|43|47|33|39|30|22|33|25|25|21|26|27|25|24|15|22|18|21|22|14|13|7|8|14|14|9|13|17|8|9|12|16|6|6|6|6|6|7|10|9|10|14|7|14|4|4|9|11|5|7|10|5|5|3|6|5|6|4|3|2|0|2|1|0|6|2|0|0|1|0|1|1|0|0|2|0|0|1</HistCounts>
      </HistItem>
    </Histograms>
  </PAMRasterBand>
</PAMDataset>
